{
  "slug": "farmer69-form-power-of-attorney-example",
  "title": "ตัวอย่างหนังสือมอบอำนาจสำหรับงานทะเบียนเกษตรกร",
  "category": "ภาคผนวก: แบบคำร้อง",
  "citation_text": "PDF หน้า 72; หน้าเอกสาร 70",
  "topics": [
    "หนังสือมอบอำนาจ",
    "ผู้มอบอำนาจ",
    "ผู้รับมอบอำนาจ",
    "อากรแสตมป์"
  ],
  "review_flags": [
    "RF-017",
    "RF-019",
    "RF-020"
  ],
  "source_pdf_pages": [
    72
  ],
  "source_printed_pages": [
    70
  ],
  "pdf_url": "https://cjjirwqoovypymndhvwt.supabase.co/storage/v1/object/public/farmer69-assets/source/farmer69-watermark.pdf",
  "body_markdown": "# ตัวอย่างหนังสือมอบอำนาจ\n\n## ข้อมูลในหนังสือ\n\n- สถานที่และวันที่ทำหนังสือ\n- ชื่อ อายุ เลขประจำตัวประชาชน ที่อยู่ และโทรศัพท์ของผู้มอบอำนาจ\n- ชื่อ อายุ เลขประจำตัวประชาชน ที่อยู่ และโทรศัพท์ของผู้รับมอบอำนาจ\n- ขอบเขตอำนาจที่เลือก เช่น ยื่นแจ้งปรับปรุงทะเบียนเกษตรกร หรือเข้าประชาคมและลงชื่อในแบบติดประกาศ\n- ลายมือชื่อผู้มอบอำนาจ ผู้รับมอบอำนาจ และพยานสองคน\n\n## ข้อกำหนดที่ระบุในตัวอย่าง\n\n- ผู้รับมอบอำนาจต้องไม่เป็นบุคคลเดียวกับพยาน เจ้าหน้าที่รับขึ้นทะเบียน เจ้าหน้าที่ตรวจแบบ หรือผู้ตรวจสอบทางสังคมหรือพื้นที่ตามที่แบบอธิบาย\n- แนบสำเนาบัตรประจำตัวประชาชนของผู้มอบและผู้รับมอบอำนาจ พร้อมรับรองสำเนา\n- ตัวอย่างระบุอากรแสตมป์ 10 บาทสำหรับการมอบอำนาจให้ทำครั้งเดียว และ 30 บาทสำหรับการมอบอำนาจให้ทำมากกว่าหนึ่งครั้ง\n- ตัวอย่างระบุระยะเวลาการใช้หนังสือมอบอำนาจ 1 ปีนับจากวันที่ได้รับมอบอำนาจ\n\n## ข้อควรระวัง\n\nอัตราอากรและข้อกำหนดทางกฎหมายในแบบเป็นข้อมูลตามคู่มือปี 2569 ก่อนนำไปใช้จริงควรตรวจข้อกำหนดปัจจุบันและแบบที่หน่วยงานใช้งาน\n\n## อ้างอิงต้นฉบับ\n\n- PDF หน้า 72\n- หน้าเอกสาร 70\n- ภาคผนวก 3 (9)\n"
}